certbot_dns_transip/.VERSION
certbot_dns_transip/__init__.py
certbot_dns_transip/_version.py
certbot_dns_transip/dns_transip.py
certbot_dns_transip-0.5.2.data/data/.VERSION
certbot_dns_transip-0.5.2.data/data/AUTHORS.rst
certbot_dns_transip-0.5.2.data/data/CONTRIBUTING.rst
certbot_dns_transip-0.5.2.data/data/HISTORY.rst
certbot_dns_transip-0.5.2.data/data/LICENSE
certbot_dns_transip-0.5.2.data/data/README.rst
certbot_dns_transip-0.5.2.data/data/USAGE.rst
certbot_dns_transip-0.5.2.dist-info/AUTHORS.rst
certbot_dns_transip-0.5.2.dist-info/LICENSE
certbot_dns_transip-0.5.2.dist-info/METADATA
certbot_dns_transip-0.5.2.dist-info/WHEEL
certbot_dns_transip-0.5.2.dist-info/entry_points.txt
certbot_dns_transip-0.5.2.dist-info/top_level.txt
certbot_dns_transip-0.5.2.dist-info/RECORD
