Metadata-Version: 2.1
Name: certbot-dns-transip
Version: 0.5.2
Summary: Certbot plugin to authenticate using dns TXT records via Transip API
Home-page: https://github.com/hsmade/certbot_dns_transip
Author: Wim Fournier
Author-email: wim@fournier.nl
License: Apache license 2.0
Keywords: certbot_dns_transip
Classifier: Development Status :: 4 - Beta
Classifier: Intended Audience :: Developers
Classifier: License :: OSI Approved :: Apache Software License
Classifier: Natural Language :: English
Classifier: Programming Language :: Python
License-File: LICENSE
License-File: AUTHORS.rst
Requires-Dist: acme (>=0.16.0)
Requires-Dist: certbot (>=0.16.0)
Requires-Dist: setuptools (>=1.0)
Requires-Dist: python-transip (==0.6.0)
